displam/__init__.py
displam/cli.py
displam/bin/displam
displam.libs/libblas-357956a1.so.3.4.2
displam.libs/libgfortran-040039e1.so.5.0.0
displam.libs/libgfortran-91cc3cb1.so.3.0.0
displam.libs/liblapack-1ad85175.so.3.4.2
displam.libs/libquadmath-96973f99.so.0.0.0
displam-1.6.0.dist-info/LICENSE
displam-1.6.0.dist-info/METADATA
displam-1.6.0.dist-info/WHEEL
displam-1.6.0.dist-info/entry_points.txt
displam-1.6.0.dist-info/RECORD
