Metadata-Version: 2.1
Name: displam
Version: 1.6.0
Summary: Calculation of the phase velocity of Lamb waves in plate composite structures
Home-page: https://gitlab.com/dlr-sy/displam
Author: Baaran, Jens
Author-email: jens.baaran@haw-hamburg.de
Maintainer: Garbade, Marc
Maintainer-email: marc.garbade@dlr.de
Project-URL: Repository, https://gitlab.com/dlr-sy/displam
Keywords: analysis,monitoring,composite
Classifier: Development Status :: 7 - Inactive
Classifier: Topic :: Scientific/Engineering
Classifier: Programming Language :: Python :: 2
Classifier: Programming Language :: Python :: 3
Classifier: License :: OSI Approved :: MIT License
Classifier: Operating System :: OS Independent
Requires-Python: >=2.7, !=3.0.*, !=3.1.*, !=3.2.*, !=3.3.*, !=3.4.*
License-File: LICENSE
